robot_azure_sync/__init__.py
robot_azure_sync/robot_azure_sync.py
robot_azure_sync/robot_azure_sync_get.py
robot_azure_sync/robot_azure_sync_patch.py
robot_azure_sync/sync_utils.py
robot_azure_sync-1.0.0.dist-info/METADATA
robot_azure_sync-1.0.0.dist-info/WHEEL
robot_azure_sync-1.0.0.dist-info/entry_points.txt
robot_azure_sync-1.0.0.dist-info/top_level.txt
robot_azure_sync-1.0.0.dist-info/RECORD
