Metadata-Version: 2.1
Name: robot_azure_sync
Version: 1.0.0
Summary: Synchronization functionalities for Azure-related tasks.
Home-page: https://github.com/fabiorisantosquispe/robot_azure_sync
Author: Fábio Ribeiro dos Santos Quispe
Author-email: fabiorisantos1981@gmail.com
License: MIT
Keywords: SYNC,SYNCHRONIZATION,ROBOT FRAMEWORK,AZURE
Classifier: Development Status :: 5 - Production/Stable
Classifier: Intended Audience :: Developers
Classifier: License :: OSI Approved :: MIT License
Classifier: Programming Language :: Python :: 3
Classifier: Programming Language :: Python :: 3.6
Classifier: Programming Language :: Python :: 3.7
Classifier: Programming Language :: Python :: 3.8
Requires-Dist: requests
